pymkdir
