Metadata-Version: 1.0
Name: pymkdir
Version: 1.1
Summary: Create python folders with __init__.py files automagically!
Home-page: https://github.com/IgooorGP/pymkdir
Author: Igor Grillo Peternella
Author-email: igor.feq@gmail.com
License: MIT
Platform: UNKNOWN
